python3_gearman/__init__.py
python3_gearman/admin_client.py
python3_gearman/admin_client_handler.py
python3_gearman/client.py
python3_gearman/client_handler.py
python3_gearman/command_handler.py
python3_gearman/compat.py
python3_gearman/connection.py
python3_gearman/connection_manager.py
python3_gearman/constants.py
python3_gearman/errors.py
python3_gearman/io.py
python3_gearman/job.py
python3_gearman/protocol.py
python3_gearman/util.py
python3_gearman/worker.py
python3_gearman/worker_handler.py
python3_gearman-0.1.0.dist-info/METADATA
python3_gearman-0.1.0.dist-info/RECORD
python3_gearman-0.1.0.dist-info/WHEEL
python3_gearman-0.1.0.dist-info/top_level.txt
