Metadata-Version: 2.1
Name: python3-gearman
Version: 0.1.0
Summary: Python 3 Gearman API - Client, worker, and admin client interfaces
Home-page: https://github.com/josiahmwalton/python3-gearman
License: Apache
Platform: UNKNOWN
Classifier: Development Status :: 5 - Production/Stable
Classifier: Intended Audience :: Developers
Classifier: License :: OSI Approved :: Apache Software License
Classifier: Natural Language :: English
Classifier: Operating System :: OS Independent
Classifier: Programming Language :: Python :: 3.5
Classifier: Topic :: Software Development :: Libraries :: Python Modules
Requires-Python: >=3
